netrun/__init__.py
netrun/cache/__init__.py
netrun/cache/cache_manager.py
netrun/cache/decorators.py
netrun/cache/memory_cache.py
netrun/cache/redis_cache.py
netrun/cache/types.py
netrun_cache-1.0.0.dist-info/METADATA
netrun_cache-1.0.0.dist-info/WHEEL
netrun_cache-1.0.0.dist-info/licenses/LICENSE
netrun_cache-1.0.0.dist-info/RECORD
