Metadata-Version: 2.4
Name: netrun-cache
Version: 1.0.0
Summary: Redis and in-memory caching patterns for Netrun Systems portfolio
Project-URL: Homepage, https://netrunsystems.com
Project-URL: Documentation, https://docs.netrunsystems.com/cache
Project-URL: Repository, https://github.com/netrunsystems/netrun-cache
Project-URL: Issues, https://github.com/netrunsystems/netrun-cache/issues
Author-email: Daniel Garza <daniel@netrunsystems.com>
License: MIT
License-File: LICENSE
Keywords: cache,caching,distributed-cache,memory-cache,performance,redis
Classifier: Development Status :: 5 - Production/Stable
Classifier: Framework :: Pydantic
Classifier: Framework :: Pydantic :: 2
Classifier: Intended Audience :: Developers
Classifier: License :: OSI Approved :: MIT License
Classifier: Programming Language :: Python :: 3
Classifier: Programming Language :: Python :: 3.10
Classifier: Programming Language :: Python :: 3.11
Classifier: Programming Language :: Python :: 3.12
Classifier: Topic :: Software Development :: Libraries :: Python Modules
Classifier: Topic :: System :: Distributed Computing
Requires-Python: >=3.10
Requires-Dist: pydantic>=2.5.0
Provides-Extra: all
Requires-Dist: redis[asyncio]>=5.0.0; extra == 'all'
Provides-Extra: dev
Requires-Dist: black>=23.12.0; extra == 'dev'
Requires-Dist: fakeredis>=2.20.0; extra == 'dev'
Requires-Dist: mypy>=1.7.0; extra == 'dev'
Requires-Dist: pre-commit>=3.6.0; extra == 'dev'
Requires-Dist: pytest-asyncio>=0.21.0; extra == 'dev'
Requires-Dist: pytest-cov>=4.1.0; extra == 'dev'
Requires-Dist: pytest-mock>=3.12.0; extra == 'dev'
Requires-Dist: pytest>=7.4.0; extra == 'dev'
Requires-Dist: ruff>=0.1.8; extra == 'dev'
Requires-Dist: types-redis>=4.6.0; extra == 'dev'
Provides-Extra: redis
Requires-Dist: redis[asyncio]>=5.0.0; extra == 'redis'
